sdoclust/__init__.py
sdoclust/clust/__init__.py
sdoclust-0.5.1.dist-info/METADATA
sdoclust-0.5.1.dist-info/WHEEL
sdoclust-0.5.1.dist-info/licenses/LICENSE
sdoclust-0.5.1.dist-info/RECORD
