Metadata-Version: 2.4
Name: sdoclust
Version: 0.5.1
Summary: outlier detection and clustering based on sparse data observers
Project-URL: Homepage, https://github.com/CN-TU/pysdoclust
Author-email: Félix Iglesias Vázquez <felix.iglesias@tuwien.ac.at>
License: MIT License
License-File: LICENSE
Classifier: License :: OSI Approved :: MIT License
Classifier: Operating System :: OS Independent
Classifier: Programming Language :: Python :: 3
Requires-Python: >=3
